DeepTaxa/__init__.py
DeepTaxa/data.py
DeepTaxa/models.py
DeepTaxa/predict.py
DeepTaxa/utils.py
DeepTaxa/genomes/GCF_017908595.1_ASM1790859v1_genomic.faa
DeepTaxa/script/check.sh
DeepTaxa/script/hmmer.sh
DeepTaxa/script/hmmer_summary.R
DeepTaxa/script/mmseqs.sh
deeptaxa-0.3.data/scripts/data.py
deeptaxa-0.3.data/scripts/hmmer.sh
deeptaxa-0.3.data/scripts/mmseqs.sh
deeptaxa-0.3.data/scripts/predict.py
deeptaxa-0.3.dist-info/METADATA
deeptaxa-0.3.dist-info/WHEEL
deeptaxa-0.3.dist-info/top_level.txt
deeptaxa-0.3.dist-info/RECORD
