Metadata-Version: 2.1
Name: deeptaxa
Version: 0.3
Summary: DeepTaxa is a deep learning tool for taxonomic classification of bacterial genomes
Home-page: https://github.com/HUST-NingKang-Lab/DeepTaxa
Author: Yuguo Zha, Haobo Zhang, Kang Ning
Author-email: hugozha@hust.edu.cn, ningkang@hust.edu.cn
Maintainer: Yuguo Zha
Maintainer-email: hugozha@hust.edu.cn
License: GPL-3.0 License
Platform: linux
Classifier: Topic :: Scientific/Engineering :: Bio-Informatics
Classifier: Operating System :: OS Independent
Classifier: License :: OSI Approved :: GNU General Public License v3 (GPLv3)
Classifier: Programming Language :: Python :: 3
Requires-Python: >=3
